MANIFEST.in
README.md
setup.py
taskcluster_s3_uploader.egg-info/PKG-INFO
taskcluster_s3_uploader.egg-info/SOURCES.txt
taskcluster_s3_uploader.egg-info/dependency_links.txt
taskcluster_s3_uploader.egg-info/requires.txt
taskcluster_s3_uploader.egg-info/top_level.txt
tc_s3_uploader/__init__.py
tc_s3_uploader/base.py