Metadata-Version: 1.0
Name: taskcluster-s3-uploader
Version: 0.3.1
Summary: Upload files to S3 with your TaskCluster authentication
Home-page: https://github.com/armenzg/treeherder_submitter
Author: Armen Zambrano G.
Author-email: armenzg@mozilla.com
License: MPL
Platform: UNKNOWN
